algoritmos_geneticos_DG_PV/__init__.py
algoritmos_geneticos_DG_PV/cruce.py
algoritmos_geneticos_DG_PV/genetico.py
algoritmos_geneticos_DG_PV/mutacion.py
algoritmos_geneticos_DG_PV/reemplazo.py
algoritmos_geneticos_DG_PV/seleccion.py
algoritmos_geneticos_dg_pv-0.1.0.dist-info/licenses/LICENSE
algoritmos_geneticos_dg_pv-0.1.0.dist-info/METADATA
algoritmos_geneticos_dg_pv-0.1.0.dist-info/WHEEL
algoritmos_geneticos_dg_pv-0.1.0.dist-info/top_level.txt
algoritmos_geneticos_dg_pv-0.1.0.dist-info/RECORD
