Metadata-Version: 2.4
Name: algoritmos_geneticos_DG_PV
Version: 0.1.0
Summary: Librería de algoritmos genéticos en español.
Home-page: https://github.com/oxgerrero/algoritmos_geneticos_DG_PV
Author: David Gomez - Paula Vera
Author-email: davidleonardogomez@ucundinamarca.edu.co
Project-URL: Documentación, https://github.com/oxgerrero/algoritmos_geneticos_DG_PV
Project-URL: Código fuente, https://github.com/oxgerrero/algoritmos_geneticos_DG_PV
Project-URL: Reportar errores, https://github.com/oxgerrero/algoritmos_geneticos_DG_PV/issues
Classifier: Programming Language :: Python :: 3
Classifier: License :: OSI Approved :: MIT License
Classifier: Operating System :: OS Independent
Classifier: Natural Language :: Spanish
Classifier: Development Status :: 4 - Beta
Classifier: Intended Audience :: Developers
Classifier: Topic :: Scientific/Engineering :: Artificial Intelligence
Requires-Python: >=3.11.8
License-File: LICENSE
Dynamic: author
Dynamic: author-email
Dynamic: classifier
Dynamic: description
Dynamic: description-content-type
Dynamic: home-page
Dynamic: license-file
Dynamic: project-url
Dynamic: requires-python
Dynamic: summary
